lightparse/__init__.py
lightparse/lightparse.py
lightparse/mappers.py
lightparse/matrixprinter.py
lightparse/terminalcolors.py
lightparse-0.3.3.dist-info/LICENSE
lightparse-0.3.3.dist-info/METADATA
lightparse-0.3.3.dist-info/WHEEL
lightparse-0.3.3.dist-info/entry_points.txt
lightparse-0.3.3.dist-info/top_level.txt
lightparse-0.3.3.dist-info/RECORD
