Metadata-Version: 2.1
Name: lightparse
Version: 0.3.3
Summary: Light to use argument parser for cli tools
Home-page: http://keeflorin.fi/lightparse/
Author: Nireco
Author-email: marko.rasa+py@paivola.fi
License: MIT
Platform: UNKNOWN
Requires-Python: >=2.7, !=3.0.*, !=3.1.*, !=3.2.*, <4
